{"cameraMode":{"drawMode":0,"name":"Shaded","section":"Shading Mode"},"sceneLighting":false,"audioPlay":false,"sceneViewState":{"m_AlwaysRefresh":false,"showFog":true,"showSkybox":true,"showFlares":true,"showImageEffects":true,"showParticleSystems":true,"showVisualEffectGraphs":true,"m_FxEnabled":false},"in2DMode":false,"pivot":{"x":1115.1336669921875,"y":1493.427978515625,"z":0.0},"rotation":{"x":-0.05540070682764053,"y":0.11685384064912796,"z":-0.00651010824367404,"w":-0.9916123151779175},"size":174.80747985839845,"orthographic":false}